esdslquerylib/__init__.py
esdslquerylib/dsl_query.py
esdslquerylib/model.py
esdslquerylib-0.0.2.dist-info/licenses/LICENSE
esdslquerylib-0.0.2.dist-info/METADATA
esdslquerylib-0.0.2.dist-info/WHEEL
esdslquerylib-0.0.2.dist-info/top_level.txt
esdslquerylib-0.0.2.dist-info/RECORD
