Metadata-Version: 2.4
Name: esdslquerylib
Version: 0.0.2
Summary: Elasticsearch query lib
Home-page: https://github.com/kejun91/esdslquerylib
Author: Jun Ke
Author-email: kejun91@gmail.com
Classifier: Programming Language :: Python :: 3
Classifier: License :: OSI Approved :: MIT License
Classifier: Operating System :: OS Independent
Requires-Python: >=3.9
License-File: LICENSE
Dynamic: author
Dynamic: author-email
Dynamic: classifier
Dynamic: description
Dynamic: description-content-type
Dynamic: home-page
Dynamic: license-file
Dynamic: requires-python
Dynamic: summary
